sdlcctl/__init__.py
sdlcctl/cli.py
sdlcctl/commands/__init__.py
sdlcctl/commands/agents.py
sdlcctl/commands/compliance.py
sdlcctl/commands/fix.py
sdlcctl/commands/generate.py
sdlcctl/commands/init.py
sdlcctl/commands/magic.py
sdlcctl/commands/migrate.py
sdlcctl/commands/plan.py
sdlcctl/commands/report.py
sdlcctl/commands/spec.py
sdlcctl/commands/validate.py
sdlcctl/lib/__init__.py
sdlcctl/lib/domain_detector.py
sdlcctl/lib/nlp_parser.py
sdlcctl/lib/progress.py
sdlcctl/lib/sse_client.py
sdlcctl/prompts/__init__.py
sdlcctl/prompts/vietnamese.py
sdlcctl/validation/__init__.py
sdlcctl/validation/base_validator.py
sdlcctl/validation/config.py
sdlcctl/validation/engine.py
sdlcctl/validation/p0.py
sdlcctl/validation/scanner.py
sdlcctl/validation/structure_scanner.py
sdlcctl/validation/tier.py
sdlcctl/validation/violation.py
sdlcctl/validation/validators/__init__.py
sdlcctl/validation/validators/cross_reference.py
sdlcctl/validation/validators/header_metadata.py
sdlcctl/validation/validators/naming_convention.py
sdlcctl/validation/validators/sequential_numbering.py
sdlcctl/validation/validators/spec_frontmatter.py
sdlcctl/validation/validators/stage_folder.py
sdlcctl-1.2.0.dist-info/METADATA
sdlcctl-1.2.0.dist-info/WHEEL
sdlcctl-1.2.0.dist-info/entry_points.txt
sdlcctl-1.2.0.dist-info/top_level.txt
sdlcctl-1.2.0.dist-info/RECORD
