Metadata-Version: 2.4
Name: sdlcctl
Version: 1.2.0
Summary: SDLC 6.0.0 Specification Validator CLI
Author-email: SDLC Orchestrator Team <sdlc@example.com>
Maintainer-email: SDLC Orchestrator Team <sdlc@example.com>
License: Apache-2.0
Project-URL: Homepage, https://github.com/sdlc-orchestrator/sdlcctl
Project-URL: Documentation, https://docs.sdlc-orchestrator.com/cli
Project-URL: Repository, https://github.com/sdlc-orchestrator/sdlcctl
Project-URL: Issues, https://github.com/sdlc-orchestrator/sdlcctl/issues
Keywords: sdlc,validation,cli,documentation,structure
Classifier: Development Status :: 4 - Beta
Classifier: Environment :: Console
Classifier: Intended Audience :: Developers
Classifier: License :: OSI Approved :: Apache Software License
Classifier: Operating System :: OS Independent
Classifier: Programming Language :: Python :: 3
Classifier: Programming Language :: Python :: 3.10
Classifier: Programming Language :: Python :: 3.11
Classifier: Programming Language :: Python :: 3.12
Classifier: Topic :: Software Development :: Documentation
Classifier: Topic :: Software Development :: Quality Assurance
Requires-Python: >=3.10
Requires-Dist: typer>=0.9.0
Requires-Dist: click<8.2
Requires-Dist: rich>=13.0.0
Requires-Dist: pyyaml>=6.0.0
Requires-Dist: jsonschema>=4.20.0
Provides-Extra: dev
Requires-Dist: pytest>=7.0.0; extra == "dev"
Requires-Dist: pytest-cov>=4.0.0; extra == "dev"
Requires-Dist: pytest-asyncio>=0.21.0; extra == "dev"
Requires-Dist: mypy>=1.0.0; extra == "dev"
Requires-Dist: ruff>=0.1.0; extra == "dev"
